xbbg/__init__.py
xbbg/blp.py
xbbg/const.py
xbbg/api/__init__.py
xbbg/api/helpers.py
xbbg/api/historical/__init__.py
xbbg/api/historical/historical.py
xbbg/api/intraday/__init__.py
xbbg/api/intraday/intraday.py
xbbg/api/realtime/__init__.py
xbbg/api/realtime/realtime.py
xbbg/api/reference/__init__.py
xbbg/api/reference/lookup.py
xbbg/api/reference/reference.py
xbbg/api/screening/__init__.py
xbbg/api/screening/screening.py
xbbg/core/__init__.py
xbbg/core/pipeline.py
xbbg/core/process.py
xbbg/core/config/__init__.py
xbbg/core/config/intervals.py
xbbg/core/config/overrides.py
xbbg/core/domain/__init__.py
xbbg/core/domain/context.py
xbbg/core/domain/contracts.py
xbbg/core/infra/__init__.py
xbbg/core/infra/blpapi_logging.py
xbbg/core/infra/blpapi_wrapper.py
xbbg/core/infra/conn.py
xbbg/core/utils/__init__.py
xbbg/core/utils/timezone.py
xbbg/core/utils/trials.py
xbbg/core/utils/utils.py
xbbg/io/__init__.py
xbbg/io/cache.py
xbbg/io/db.py
xbbg/io/files.py
xbbg/io/param.py
xbbg/markets/__init__.py
xbbg/markets/info.py
xbbg/markets/pmc.py
xbbg/markets/providers.py
xbbg/markets/resolver_chain.py
xbbg/markets/resolvers.py
xbbg/markets/cached/Comdty_cfg.parq
xbbg/markets/cached/Curncy_cfg.parq
xbbg/markets/cached/Equity_cfg.parq
xbbg/markets/cached/Index_cfg.parq
xbbg/markets/cached/assets.parq
xbbg/markets/cached/ccy.parq
xbbg/markets/cached/ccy_cfg.parq
xbbg/markets/cached/exch.parq
xbbg/markets/cached/exch_cfg.parq
xbbg/markets/cached/pmc_cache.json
xbbg/markets/config/assets.yml
xbbg/markets/config/ccy.yml
xbbg/markets/config/exch.yml
xbbg/utils/__init__.py
xbbg/utils/pipeline.py
xbbg-0.10.3.dist-info/licenses/LICENSE
xbbg-0.10.3.dist-info/METADATA
xbbg-0.10.3.dist-info/WHEEL
xbbg-0.10.3.dist-info/top_level.txt
xbbg-0.10.3.dist-info/RECORD
