Metadata-Version: 2.4
Name: xbbg
Version: 0.10.3
Summary: Intuitive Bloomberg data API
Author-email: Alpha x1 <alpha.xone@outlook.com>
License-Expression: Apache-2.0
Project-URL: Homepage, https://github.com/alpha-xone/xbbg
Project-URL: Documentation, https://xbbg.readthedocs.io/
Project-URL: Source, https://github.com/alpha-xone/xbbg
Project-URL: Issues, https://github.com/alpha-xone/xbbg/issues
Project-URL: Logo, https://raw.githubusercontent.com/alpha-xone/xbbg/main/docs/xbbg.png
Classifier: Development Status :: 5 - Production/Stable
Classifier: Intended Audience :: Financial and Insurance Industry
Classifier: Intended Audience :: Developers
Classifier: Topic :: Office/Business :: Financial
Classifier: Topic :: Office/Business :: Financial :: Investment
Classifier: Topic :: Software Development :: Libraries :: Python Modules
Classifier: Topic :: Scientific/Engineering :: Information Analysis
Classifier: Operating System :: OS Independent
Classifier: Programming Language :: Python :: 3
Classifier: Programming Language :: Python :: 3.10
Classifier: Programming Language :: Python :: 3.11
Classifier: Programming Language :: Python :: 3.12
Classifier: Programming Language :: Python :: 3.13
Classifier: Programming Language :: Python :: 3.14
Requires-Python: <3.15,>=3.10
License-File: LICENSE
Requires-Dist: numpy>=2.2.6
Requires-Dist: pandas>=2.0
Requires-Dist: pandas-market-calendars>=5.1.3
Requires-Dist: pyarrow>=22.0.0
Requires-Dist: pytest>=8.4.2
Requires-Dist: python-stdnum>=2.1
Requires-Dist: pytz>=2025.2
Requires-Dist: ruamel.yaml>=0.18.16
Provides-Extra: test
Requires-Dist: pytest; extra == "test"
Requires-Dist: pytest-cov; extra == "test"
Requires-Dist: coverage; extra == "test"
Requires-Dist: codecov; extra == "test"
Provides-Extra: dev
Requires-Dist: ruff; extra == "dev"
Requires-Dist: ipykernel; extra == "dev"
Requires-Dist: build; extra == "dev"
Requires-Dist: twine; extra == "dev"
Requires-Dist: pre-commit; extra == "dev"
Provides-Extra: docs
Requires-Dist: sphinx>=5.3.0; extra == "docs"
Requires-Dist: sphinx-rtd-theme>=2.0.0; extra == "docs"
Requires-Dist: sphinx-llms-txt>=0.7.0; extra == "docs"
Dynamic: license-file
